gchar/__init__.py
gchar/config/__init__.py
gchar/config/meta.py
gchar/games/__init__.py
gchar/games/arknights/__init__.py
gchar/games/arknights/character.py
gchar/games/arknights/name.py
gchar/games/arknights/property.py
gchar/games/azurlane/__init__.py
gchar/games/azurlane/character.py
gchar/games/azurlane/name.py
gchar/games/azurlane/property.py
gchar/games/base/__init__.py
gchar/games/base/character.py
gchar/games/base/name.py
gchar/games/base/property.py
gchar/games/base/skin.py
gchar/games/bluearchive/__init__.py
gchar/games/bluearchive/character.py
gchar/games/bluearchive/name.py
gchar/games/bluearchive/property.py
gchar/games/dispatch/__init__.py
gchar/games/dispatch/access.py
gchar/games/fgo/__init__.py
gchar/games/fgo/character.py
gchar/games/fgo/name.py
gchar/games/fgo/property.py
gchar/games/genshin/__init__.py
gchar/games/genshin/character.py
gchar/games/genshin/name.py
gchar/games/genshin/property.py
gchar/games/girlsfrontline/__init__.py
gchar/games/girlsfrontline/character.py
gchar/games/girlsfrontline/name.py
gchar/games/girlsfrontline/property.py
gchar/games/neuralcloud/__init__.py
gchar/games/neuralcloud/character.py
gchar/games/neuralcloud/name.py
gchar/games/neuralcloud/property.py
gchar/games/nikke/__init__.py
gchar/games/nikke/character.py
gchar/games/nikke/name.py
gchar/games/nikke/property.py
gchar/games/pathtonowhere/__init__.py
gchar/games/pathtonowhere/character.py
gchar/games/pathtonowhere/name.py
gchar/games/pathtonowhere/property.py
gchar/games/starrail/__init__.py
gchar/games/starrail/character.py
gchar/games/starrail/name.py
gchar/games/starrail/property.py
gchar/resources/__init__.py
gchar/resources/pixiv/__init__.py
gchar/resources/pixiv/base.py
gchar/resources/pixiv/keyword.py
gchar/resources/pixiv/tag.py
gchar/resources/sites/__init__.py
gchar/resources/sites/base.py
gchar/resources/sites/tags.py
gchar/utils/__init__.py
gchar/utils/cache.py
gchar/utils/cli.py
gchar/utils/compare.py
gchar/utils/download.py
gchar/utils/session.py
gchar-0.1.1.dist-info/LICENSE
gchar-0.1.1.dist-info/METADATA
gchar-0.1.1.dist-info/WHEEL
gchar-0.1.1.dist-info/top_level.txt
gchar-0.1.1.dist-info/RECORD
